primarymath/__init__.py
primarymath/number.py
primarymath-0.1.2.dist-info/METADATA
primarymath-0.1.2.dist-info/WHEEL
primarymath-0.1.2.dist-info/licenses/LICENSE
primarymath-0.1.2.dist-info/RECORD
