Metadata-Version: 2.1
Name: primarymath
Version: 0.1.2
Summary: A library for elementary math stuff based on the book Everything You Need to Ace Math.
Project-URL: Homepage, https://github.com/ajunior/primarymath
Project-URL: GitHub Repository, https://github.com/ajunior/primarymath
Project-URL: Bug Tracker, https://github.com/ajunior/primarymath/issues
Author-email: Adjamilton Junior <jr@ieee.org>
License-File: LICENSE
Classifier: Development Status :: 5 - Production/Stable
Classifier: Intended Audience :: Education
Classifier: Intended Audience :: Other Audience
Classifier: License :: OSI Approved :: MIT License
Classifier: Natural Language :: English
Classifier: Operating System :: OS Independent
Classifier: Programming Language :: Python :: 3.11
Classifier: Topic :: Education
Classifier: Topic :: Scientific/Engineering :: Mathematics
Classifier: Topic :: Software Development :: Libraries
Classifier: Topic :: Utilities
Requires-Python: >=3.11
